Metadata-Version: 1.1
Name: topsis53004pack1
Version: 0.1
Summary: Library that implements the "The Technique for Order of Preference by Similarity to Ideal Solution (TOPSIS)"
Home-page: https://github.com/Ashutosh2088/topsis53004pack1
Author: Ashutosh Rattan
Author-email: ashutosh544@gmail.com
License: MIT
Download-URL: https://github.com/Ashutosh2088/topsis53004pack1/archive/v0.1.tar.gz
Platform: UNKNOWN
Classifier: Development Status :: 3 - Alpha
Classifier: Intended Audience :: Developers
Classifier: Topic :: Software Development :: Build Tools
Classifier: License :: OSI Approved :: MIT License
Classifier: Programming Language :: Python :: 3
Classifier: Programming Language :: Python :: 3.4
Classifier: Programming Language :: Python :: 3.5
Classifier: Programming Language :: Python :: 3.6
